[
		{
            "title": "Hollow Knight",
            "system": "Xbox One",
            "date_completed": "July 10, 2019"
        },
        {
            "title": "World of Warcraft",
            "system": "PC",
            "date_completed": "April 30, 2020"
        },
        {
            "title": "God of War",
            "system": "Playstation 4",
            "date_completed": "August 2, 2018"
        },
        {
            "title": "Call of Duty: Modern Warfare",
            "system": "Xbox One",
            "date_completed": "March 12, 2020"
        },
        {
            "title": "Minecraft",
            "system": "Xbox One",
            "date_completed": "Octocber 31, 2020"
        },
        {
            "title": "Sekiro: Shadows Die Twice",
            "system": "Xbox One",
            "date_completed": "December 29, 2020"
        },
        {
            "title": "Celeste",
            "system": "Nintendo Switch",
            "date_completed": "November 12, 2019"
        },
        {
            "title": "The Legend of Zelda: Breath of the Wild",
            "system": "Nintendo Switch",
            "date_completed": "May 12, 2018"
        },
        {
            "title": "Destiny 2",
            "system": "Xbox One",
            "date_completed": "September 19, 2019"
        },
        {
            "title": "Mario Odyssey",
            "system": "Nintendo Switch",
            "date_completed": "April 12, 2018"
        },
        {
            "title": "Death Stranding",
            "system": "Playstation 4",
            "date_completed": "February 12, 2020"
        },
        {
            "title": "Spiderman",
            "system": "Playstation 4",
            "date_completed": "July 12, 2019"
        },
        {
            "title": "Red Dead Redemption 2",
            "system": "Xbox One",
            "date_completed": "November 5, 2018"
        }
	]